Metadata-Version: 2.1
Name: odoo14-addon-stock_quant_history_queued
Version: 14.0.1.0.1.dev5
Summary: Use Queue jop to generate stock quants snapshots
Home-page: https://github.com/OCA/stock-logistics-reporting
Author: Pierre Verkest <pierreverkest84@gmail.com>, Odoo Community Association (OCA)
Author-email: support@odoo-community.org
License: AGPL-3
Classifier: Programming Language :: Python
Classifier: Framework :: Odoo
Classifier: Framework :: Odoo :: 14.0
Classifier: License :: OSI Approved :: GNU Affero General Public License v3
Requires-Python: >=3.6
Requires-Dist: odoo14-addon-queue-job
Requires-Dist: odoo14-addon-stock-quant-history
Requires-Dist: odoo<14.1dev,>=14.0a
